fewsio/__init__.py
fewsio/_version.py
fewsio/common.py
fewsio/data_config.py
fewsio/pi.py
fews_io-0.0.4.dist-info/COPYING.LESSER
fews_io-0.0.4.dist-info/METADATA
fews_io-0.0.4.dist-info/WHEEL
fews_io-0.0.4.dist-info/top_level.txt
fews_io-0.0.4.dist-info/RECORD
