Metadata-Version: 2.1
Name: fews-io
Version: 0.0.4
Summary: Library for communicating with Delft-FEWS
Home-page: https://oss.deltares.nl/web/delft-fews
Author: Tjerk Vreeken
Author-email: tjerk.vreeken@deltares.nl
Maintainer: Tjerk Vreeken
License: LGPLv3
Keywords: fews deltares xml
Platform: Windows
Platform: Linux
Platform: Mac OS-X
Platform: Unix
Classifier: Development Status :: 4 - Beta
Classifier: Intended Audience :: Science/Research
Classifier: Intended Audience :: Information Technology
Classifier: License :: OSI Approved :: GNU Lesser General Public License v3 (LGPLv3)
Classifier: Programming Language :: Other
Classifier: Topic :: Scientific/Engineering :: GIS
Classifier: Topic :: Scientific/Engineering :: Mathematics
Classifier: Topic :: Scientific/Engineering :: Physics
Classifier: Operating System :: Microsoft :: Windows
Classifier: Operating System :: POSIX
Classifier: Operating System :: Unix
Classifier: Operating System :: MacOS
Requires-Python: >=3.7
License-File: COPYING.LESSER
Requires-Dist: numpy >=1.16.0
